somu-1.3.0.dist-info/METADATA
somu-1.3.0.dist-info/WHEEL
somu-1.3.0.dist-info/licenses/LICENSE
somu.libs/libOpenCL-1552ec44.so.1
somu.libs/libaf-3cd91a14.so.3
somu.libs/libiomp5-1bef3c4b.so
somu.libs/libmkl_core-0b91374c.so
somu.libs/libmkl_intel_lp64-6bcd9cb5.so
somu.libs/libmkl_intel_thread-13011518.so
somu/py.typed
somu/somu.pyi
somu/__init__.py
somu/torchsom.py
somu/somu.abi3.so
somu-1.3.0.dist-info/RECORD
