Metadata-Version: 2.4
Name: somu
Version: 1.3.0
Classifier: Programming Language :: Rust
Classifier: Programming Language :: Python :: Implementation :: CPython
Classifier: Programming Language :: Python :: Implementation :: PyPy
Requires-Dist: tqdm>=4.0.0
Requires-Dist: torch>=2.0.0
Requires-Dist: numpy>=0.23.0
License-File: LICENSE
License-File: LICENSE
Summary: A simple high-performance implementation of the Self-Organizing Map (SOM) algorithm in Rust, exposed as a Python module.
Author: Jakub Skalski
Author-email: jakub.skalski.cs@com>
Requires-Python: >=3.8
Project-URL: Source Code, https://github.com/ventus550/somu
